llcp_env/__init__.py
llcp_env/envs/__init__.py
llcp_env/envs/env_llcp.py
llcp_env-4.0.1.dist-info/METADATA
llcp_env-4.0.1.dist-info/WHEEL
llcp_env-4.0.1.dist-info/top_level.txt
llcp_env-4.0.1.dist-info/RECORD
