Metadata-Version: 2.1
Name: llcp-env
Version: 4.0.1
Summary: A OpenAI Gym Env for gym
Home-page: UNKNOWN
License: UNKNOWN
Platform: UNKNOWN
Requires-Dist: gym
